pyward/__init__.py
pyward/analyzer.py
pyward/cli.py
pyward/fixer/__init__.py
pyward/fixer/fix_imports.py
pyward/format/__init__.py
pyward/format/formatter.py
pyward/optimization/__init__.py
pyward/optimization/run.py
pyward/optimization/rules/__init__.py
pyward/optimization/rules/append_in_loop.py
pyward/optimization/rules/deeply_nested_loops.py
pyward/optimization/rules/dict_comprehension.py
pyward/optimization/rules/genexpr_vs_list.py
pyward/optimization/rules/len_call_in_loop.py
pyward/optimization/rules/list_build_then_copy.py
pyward/optimization/rules/membership_on_list_in_loop.py
pyward/optimization/rules/open_without_context.py
pyward/optimization/rules/range_len_pattern.py
pyward/optimization/rules/set_comprehension.py
pyward/optimization/rules/sort_assignment.py
pyward/optimization/rules/string_concat_in_loop.py
pyward/optimization/rules/unreachable_code.py
pyward/optimization/rules/unused_imports.py
pyward/optimization/rules/unused_variables.py
pyward/security/__init__.py
pyward/security/run.py
pyward/security/rules/__init__.py
pyward/security/rules/exec_eval.py
pyward/security/rules/hardcoded_secrets.py
pyward/security/rules/pickle_usage.py
pyward/security/rules/python_json_logger.py
pyward/security/rules/ssl_verification.py
pyward/security/rules/subprocess_usage.py
pyward/security/rules/url_open_usage.py
pyward/security/rules/weak_hashing_usage.py
pyward/security/rules/yaml_load.py
pyward_cli-0.2.1.dist-info/licenses/LICENSE
pyward_cli-0.2.1.dist-info/METADATA
pyward_cli-0.2.1.dist-info/WHEEL
pyward_cli-0.2.1.dist-info/entry_points.txt
pyward_cli-0.2.1.dist-info/top_level.txt
pyward_cli-0.2.1.dist-info/RECORD
