Metadata-Version: 2.4
Name: pyward-cli
Version: 0.2.1
Summary: A CLI linter for Python that flags optimization and security issues
Home-page: https://github.com/karanlvm/pyward-cli
Author: Karan Vasudevamurthy
Author-email: karanlvm123@gmail.com
License: MIT
Project-URL: Source, https://github.com/karanlvm/pyward-cli
Project-URL: Documentation, https://github.com/karanlvm/pyward-cli#readme
Project-URL: Issue Tracker, https://github.com/karanlvm/pyward-cli/issues
Keywords: python lint cli security optimization
Classifier: Development Status :: 4 - Beta
Classifier: Intended Audience :: Developers
Classifier: Topic :: Software Development :: Quality Assurance
Classifier: Programming Language :: Python :: 3
Classifier: Programming Language :: Python :: 3.7
Classifier: Programming Language :: Python :: 3.8
Classifier: Programming Language :: Python :: 3.9
Classifier: Programming Language :: Python :: 3.10
Classifier: License :: OSI Approved :: MIT License
Classifier: Operating System :: OS Independent
Requires-Python: >=3.7
License-File: LICENSE
Requires-Dist: colorama>=0.4.6
Requires-Dist: astroid>=3.0.0
Dynamic: author
Dynamic: author-email
Dynamic: classifier
Dynamic: description
Dynamic: description-content-type
Dynamic: home-page
Dynamic: keywords
Dynamic: license
Dynamic: license-file
Dynamic: project-url
Dynamic: requires-dist
Dynamic: requires-python
Dynamic: summary
